FatigueDS/__init__.py
FatigueDS/spectrum.py
FatigueDS/tools.py
fatigueds-0.3.0.dist-info/METADATA
fatigueds-0.3.0.dist-info/WHEEL
fatigueds-0.3.0.dist-info/RECORD
