Metadata-Version: 2.4
Name: FatigueDS
Version: 0.3.0
Summary: Fatigue Damage Spectrum (FDS) and Extreme Response Spectrum (ERS)
Project-URL: homepage, https://github.com/ladisk/FatigueDS
Project-URL: documentation, https://fatigueds.readthedocs.io/en/latest/
Project-URL: source, https://github.com/ladisk/FatigueDS
Author-email: "Jaša Šonc, Martin Česnik, Rok Pavlin, Janko Slavič" <janko.slavic@fs.uni-lj.si>
Maintainer-email: "Jaša Šonc, Janko Slavič" <jasasonc@gmail.com>
License-Expression: MIT
Keywords: extreme response spectrum,fatigue damage spectrum,vibration fatigue
Classifier: Development Status :: 4 - Beta
Classifier: Intended Audience :: Developers
Classifier: License :: OSI Approved :: MIT License
Classifier: Programming Language :: Python :: 3.10
Classifier: Topic :: Scientific/Engineering
Requires-Python: >=3.10
Requires-Dist: flife
Requires-Dist: matplotlib>=3.0.0
Requires-Dist: numpy>=2.0.0
Requires-Dist: pyexsi
Requires-Dist: rainflow
Requires-Dist: scipy>=1.0.0
Requires-Dist: tqdm
Provides-Extra: dev
Requires-Dist: build; extra == 'dev'
Requires-Dist: pytest; extra == 'dev'
Requires-Dist: sphinx; extra == 'dev'
Requires-Dist: sphinx-book-theme; extra == 'dev'
Requires-Dist: sphinx-copybutton; extra == 'dev'
Requires-Dist: twine; extra == 'dev'
Requires-Dist: wheel; extra == 'dev'
